[
    {"countryname":"India","countrycode":"+91"},
    {"countryname":"Singapore","countrycode":"+65"},
    {"countryname":"Brazil","countrycode":"+55"},
    {"countryname":"Indonesia","countrycode":"+62"},
    {"countryname":"Philipines","countrycode":"+63"},
    {"countryname":"Afghanistan","countrycode":"+93"},
    {"countryname":"Albania","countrycode":"+355"},
    {"countryname":"Algeria","countrycode":"+213"},
    {"countryname":"AmericanSamoa","countrycode":"+1684"},
    {"countryname":"Andorra","countrycode":"+376"},
    {"countryname":"Angola","countrycode":"+244"},
    {"countryname":"Anguilla","countrycode":"+1264"},
    {"countryname":"Antartica","countrycode":"+672"},
    {"countryname":"Antigua and Barbuda","countrycode":"+1268"},
    {"countryname":"Argentina","countrycode":"+54"},
    {"countryname":"Armenia","countrycode":"+374"},
    {"countryname":"Aruba","countrycode":"+297"},
    {"countryname":"Australia","countrycode":"+61"},
    {"countryname":"Austria","countrycode":"+43"},
    {"countryname":"Azerbaijan","countrycode":"+994"},
    {"countryname":"Bahamas","countrycode":"+1242"},
    {"countryname":"Bahrain","countrycode":"+973"},
    {"countryname":"Bangladesh","countrycode":"+880"},
    {"countryname":"Barbados","countrycode":"+1246"},
    {"countryname":"Belarus","countrycode":"+375"},
    {"countryname":"Belgium","countrycode":"+32"},
    {"countryname":"Belize","countrycode":"+501"},
    {"countryname":"Benin","countrycode":"+229"},
    {"countryname":"Bermuda","countrycode":"+1441"},
    {"countryname":"Bhutan","countrycode":"+975"},
    {"countryname":"Bolivia, Plurinational State of","countrycode":"+591"},
    {"countryname":"Bosnia and Herzegovina","countrycode":"+387"},
    {"countryname":"Botswana","countrycode":"+267"},
    {"countryname":"British Indian Ocean Territory","countrycode":"+246"},
    {"countryname":"Brunei Darussalam","countrycode":"+673"},
    {"countryname":"Bulgaria","countrycode":"+359"},
    {"countryname":"Burkina Faso","countrycode":"+226"},
    {"countryname":"Burundi","countrycode":"+257"},
    {"countryname":"Cambodia","countrycode":"+855"},
    {"countryname":"Cameroon","countrycode":"+237"},
    {"countryname":"Canada","countrycode":"+1"},
    {"countryname":"Cape Verde","countrycode":"+238"},
    {"countryname":"Cayman Island","countrycode":"+345"},
    {"countryname":"Central African Republic","countrycode":"+236"},
    {"countryname":"Chad","countrycode":"+235"},
    {"countryname":"Chile","countrycode":"+56"},
    {"countryname":"China","countrycode":"+86"},
    {"countryname":"Christmas Island","countrycode":"+61"},
    {"countryname":"Cocos (Keeling) Island","countrycode":"+61"},
    {"countryname":"Colombia","countrycode":"+57"},
    {"countryname":"Comoros","countrycode":"+269"},
    {"countryname":"Congo","countrycode":"+242"},
    {"countryname":"Congo, the Democratic Republic","countrycode":"+243"},
    {"countryname":"Cook Island","countrycode":"+682"},
    {"countryname":"Costa Rica","countrycode":"+506"},
    {"countryname":"Cote d'Ivorie","countrycode":"+225"},
    {"countryname":"Croatia","countrycode":"+385"},
    {"countryname":"Cuba","countrycode":"+53"},
    {"countryname":"Cyprus","countrycode":"+537"},
    {"countryname":"Czech Republic","countrycode":"+420"},
    {"countryname":"Denmark","countrycode":"+45"},
    {"countryname":"Djibouti","countrycode":"+253"},
    {"countryname":"Dominica","countrycode":"+1767"},
    {"countryname":"Dominican Republic","countrycode":"+1849"},
    {"countryname":"Ecuador","countrycode":"+593"},
    {"countryname":"Egypt","countrycode":"+20"},
    {"countryname":"El Salvador","countrycode":"+503"},
    {"countryname":"Equatorial Guinea","countrycode":"+240"},
    {"countryname":"Eritrea","countrycode":"+291"},
    {"countryname":"Estonia","countrycode":"+372"},
    {"countryname":"Ethiopia","countrycode":"+251"},
    {"countryname":"Falkland Island (Malvinas)","countrycode":"+500"},
    {"countryname":"Faroe Island","countrycode":"+298"},
    {"countryname":"Fiji","countrycode":"+679"},
    {"countryname":"Finland","countrycode":"+358"},
    {"countryname":"France","countrycode":"+33"},
    {"countryname":"French Guiana","countrycode":"+594"},
    {"countryname":"French Polynesia","countrycode":"+689"},
    {"countryname":"Gabon","countrycode":"+241"},
    {"countryname":"Gambia","countrycode":"+220"},
    {"countryname":"Georgia","countrycode":"+995"},
    {"countryname":"Germany","countrycode":"+49"},
    {"countryname":"Ghana","countrycode":"+233"},
    {"countryname":"Gibraltar","countrycode":"+350"},
    {"countryname":"Greece","countrycode":"+30"},
    {"countryname":"Greenland","countrycode":"+299"},
    {"countryname":"Grenada","countrycode":"+1473"},
    {"countryname":"Guadeloupe","countrycode":"+590"},
    {"countryname":"Guam","countrycode":"+1671"},
    {"countryname":"Guatemala","countrycode":"+502"},
    {"countryname":"Guernsey","countrycode":"+44"},
    {"countryname":"Guinea","countrycode":"+224"},
    {"countryname":"Guinea-Bissau","countrycode":"+245"},
    {"countryname":"Guyana","countrycode":"+595"},
    {"countryname":"Haiti","countrycode":"+509"},
    {"countryname":"Holy See (Vatican City State)","countrycode":"+379"},
    {"countryname":"Honduras","countrycode":"+504"},
    {"countryname":"Hong Kong","countrycode":"+852"},
    {"countryname":"Hungary","countrycode":"+36"},
    {"countryname":"Iceland","countrycode":"+354"},
    {"countryname":"Iran, Islamic Republic of","countrycode":"+98"},
    {"countryname":"Iraq","countrycode":"+964"},
    {"countryname":"Ireland","countrycode":"+353"},
    {"countryname":"Isle of Man","countrycode":"+44"},
    {"countryname":"Israel","countrycode":"+972"},
    {"countryname":"Italy","countrycode":"+39"},
    {"countryname":"Jamaica","countrycode":"+1876"},
    {"countryname":"Japan","countrycode":"+81"},
    {"countryname":"Jersey","countrycode":"+44"},
    {"countryname":"Jordan","countrycode":"+962"},
    {"countryname":"Kazakhstan","countrycode":"+77"},
    {"countryname":"Kenya","countrycode":"+254"},
    {"countryname":"Kiribati","countrycode":"+686"},
    {"countryname":"Korea, Democratic People's Republic of","countrycode":"+850"},
    {"countryname":"Korea, Republic of","countrycode":"+82"},
    {"countryname":"Kuwait","countrycode":"+965"},
    {"countryname":"Kyrgyzstan","countrycode":"+996"},
    {"countryname":"Lao People's Democratic Republic","countrycode":"+856"},
    {"countryname":"Latvia","countrycode":"+371"},
    {"countryname":"Lebanon","countrycode":"+961"},
    {"countryname":"Lesotho","countrycode":"+266"},
    {"countryname":"Liberia","countrycode":"+231"},
    {"countryname":"Libyan Arab Jamahiriya","countrycode":"+218"},
    {"countryname":"Liechtenstein","countrycode":"+423"},
    {"countryname":"Lithuania","countrycode":"+370"},
    {"countryname":"Luxembourg","countrycode":"+352"},
    {"countryname":"Macao","countrycode":"+853"},
    {"countryname":"Macedonia, The Former Yugoslovia","countrycode":"+389"},
    {"countryname":"Madagascar","countrycode":"+261"},
    {"countryname":"Malawi","countrycode":"+265"},
    {"countryname":"Malaysia","countrycode":"+60"},
    {"countryname":"Maldives","countrycode":"+960"},
    {"countryname":"Mali","countrycode":"+223"},
    {"countryname":"Malta","countrycode":"+356"},
    {"countryname":"Marshall Islands","countrycode":"+692"},
    {"countryname":"Martinique","countrycode":"+596"},
    {"countryname":"Mauirania","countrycode":"+222"},
    {"countryname":"Mauritius","countrycode":"+230"},
    {"countryname":"Mayotte","countrycode":"+262"},
    {"countryname":"Mexico","countrycode":"+52"},
    {"countryname":"Micronesia, Federated States of","countrycode":"+691"},
    {"countryname":"Moldova, Republic of","countrycode":"+373"},
    {"countryname":"Monaco","countrycode":"+377"},
    {"countryname":"Mongolia","countrycode":"+976"},
    {"countryname":"Montenegro","countrycode":"+382"},
    {"countryname":"Montserrat","countrycode":"+1664"},
    {"countryname":"Morocco","countrycode":"+212"},
    {"countryname":"Mozambique","countrycode":"+258"},
    {"countryname":"Myanmar","countrycode":"+95"},
    {"countryname":"Namibia","countrycode":"+264"},
    {"countryname":"Nauru","countrycode":"+674"},
    {"countryname":"Nepal","countrycode":"+977"},
    {"countryname":"Netherlands","countrycode":"+31"},
    {"countryname":"Nertherlands Antilles","countrycode":"+599"},
    {"countryname":"New Caledonia","countrycode":"+687"},
    {"countryname":"New Zealand","countrycode":"+64"},
    {"countryname":"Nicaragua","countrycode":"+505"},
    {"countryname":"Niger","countrycode":"+227"},
    {"countryname":"Nigeria","countrycode":"+234"},
    {"countryname":"Niue","countrycode":"+683"},
    {"countryname":"Norfolk Island","countrycode":"+672"},
    {"countryname":"Northern Mariana Islands","countrycode":"+1670"},
    {"countryname":"Norway","countrycode":"+47"},
    {"countryname":"Oman","countrycode":"+968"},
    {"countryname":"Pakistan","countrycode":"+92"},
    {"countryname":"Palau","countrycode":"+680"},
    {"countryname":"Palestinian Territory, Occupied","countrycode":"+970"},
    {"countryname":"Panama","countrycode":"+507"},
    {"countryname":"Papua New Guinea","countrycode":"+675"},
    {"countryname":"Paraguay","countrycode":"+595"},
    {"countryname":"Peru","countrycode":"+51"},
    {"countryname":"Pitcairn","countrycode":"+872"},
    {"countryname":"Poland","countrycode":"+48"},
    {"countryname":"Qatar","countrycode":"+974"},
    {"countryname":"Romania","countrycode":"+40"},
    {"countryname":"Russia","countrycode":"+7"},
    {"countryname":"Rwanda","countrycode":"+250"},
    {"countryname":"Reunion","countrycode":"+262"},
    {"countryname":"Saint Barthelemy","countrycode":"+590"},
    {"countryname":"Saint Helena, Ascension and Tri...","countrycode":"+290"},
    {"countryname":"Saint Kitts and Nevis","countrycode":"+1869"},
    {"countryname":"Saint Lucia","countrycode":"+1758"},
    {"countryname":"Saint Martin","countrycode":"+590"},
    {"countryname":"Saint Pierre and Miquelon","countrycode":"+508"},
    {"countryname":"Saint Vincent and Grenadines","countrycode":"+1784"},
    {"countryname":"Samoa","countrycode":"+685"},
    {"countryname":"San Marino","countrycode":"+378"},
    {"countryname":"Sao Tome and Principe","countrycode":"+239"},
    {"countryname":"Saudi Arabia","countrycode":"+966"},
    {"countryname":"Senegal","countrycode":"+221"},
    {"countryname":"Serbia","countrycode":"+381"},
    {"countryname":"Seychelles","countrycode":"+248"},
    {"countryname":"Sierra Leone","countrycode":"+232"},
    {"countryname":"Slovakia","countrycode":"+421"},
    {"countryname":"Slovenia","countrycode":"+386"},
    {"countryname":"Solomon Islands","countrycode":"+677"},
    {"countryname":"Somalia","countrycode":"+252"},
    {"countryname":"South Africa","countrycode":"+27"},
    {"countryname":"South Georgia and South S...","countrycode":"+500"},
    {"countryname":"Spain","countrycode":"+34"},
    {"countryname":"Sri Lanka","countrycode":"+94"},
    {"countryname":"Sudan","countrycode":"+249"},
    {"countryname":"Suriname","countrycode":"+597"},
    {"countryname":"Svalbard and Jan Mayen","countrycode":"+47"},
    {"countryname":"Swaziland","countrycode":"+268"},
    {"countryname":"Sweden","countrycode":"+46"},
    {"countryname":"Switzerland","countrycode":"+41"},
    {"countryname":"Syrian Arab Republic","countrycode":"+963"},
    {"countryname":"Taiwan, Province of China","countrycode":"+886"},
    {"countryname":"Tajikistan","countrycode":"+992"},
    {"countryname":"Tazania, United Republic of","countrycode":"+255"},
    {"countryname":"Thailand","countrycode":"+66"},
    {"countryname":"Timor-Leste","countrycode":"+670"},
    {"countryname":"Togo","countrycode":"+228"},
    {"countryname":"Tokelau","countrycode":"+690"},
    {"countryname":"Tonga","countrycode":"+676"},
    {"countryname":"Trinidad and Tobago","countrycode":"+1868"},
    {"countryname":"Tunisia","countrycode":"+216"},
    {"countryname":"Turkey","countrycode":"+90"},
    {"countryname":"Turkmenistan","countrycode":"+993"},
    {"countryname":"Turks and Caicos Islands","countrycode":"+1649"},
    {"countryname":"Tuvalu","countrycode":"+688"},
    {"countryname":"Uganda","countrycode":"+256"},
    {"countryname":"Ukraine","countrycode":"+380"},
    {"countryname":"United Arab Emirates","countrycode":"+971"},
    {"countryname":"United Kingdom","countrycode":"+44"},
    {"countryname":"United States","countrycode":"+1"},
    {"countryname":"Uruguay","countrycode":"+598"},
    {"countryname":"Uzbekistan","countrycode":"+998"},
    {"countryname":"Vanuatu","countrycode":"+678"},
    {"countryname":"Venezuela, Bolivarian","countrycode":"+58"},
    {"countryname":"Viet Nam","countrycode":"+84"},
    {"countryname":"Virgin Islands, British","countrycode":"+1284"},
    {"countryname":"Virgin Islands, U.S.","countrycode":"+1340"},
    {"countryname":"Wallis and Futuna","countrycode":"+681"},
    {"countryname":"Yemen","countrycode":"+967"},
    {"countryname":"Zambia","countrycode":"+260"},
    {"countryname":"Zimbabwe","countrycode":"+263"}










]
